s3ping/__init__.py
s3ping/config/__init__.py
s3ping/config/constants.py
s3ping/core/__init__.py
s3ping/core/exporter/base.py
s3ping/core/exporter/default.py
s3ping/core/parser/base.py
s3ping/core/parser/default.py
s3ping/core/parser/html.py
s3ping/core/pipeline/scrape.py
s3ping/core/scrape/http_client.py
s3ping/core/utils/logger.py
s3ping/core/utils/utils.py
s3ping/middlewares/__init__.py
s3ping/middlewares/base.py
s3ping/middlewares/captcha.py
s3ping/middlewares/header.py
s3ping/middlewares/proxy.py
s3ping/middlewares/retry.py
s3ping/middlewares/selenium.py
s3ping-0.1.0.dist-info/METADATA
s3ping-0.1.0.dist-info/WHEEL
s3ping-0.1.0.dist-info/top_level.txt
s3ping-0.1.0.dist-info/RECORD
